MANIFEST.in
README.md
setup.py
FireDeamon/__init__.py
FireDeamon/cpp.i
FireDeamon/cpp.py
FireDeamon.egg-info/PKG-INFO
FireDeamon.egg-info/SOURCES.txt
FireDeamon.egg-info/dependency_links.txt
FireDeamon.egg-info/requires.txt
FireDeamon.egg-info/top_level.txt
FireDeamon/visualize/__init__.py
FireDeamon/visualize/cpp.i
FireDeamon/visualize/cpp.py
include/FireDeamon/core/arbitrary_grid_local_minima.h
include/FireDeamon/core/constants.h
include/FireDeamon/core/deamon_functors.h
include/FireDeamon/core/electron_density.h
include/FireDeamon/core/electrostatic_potential_charges.h
include/FireDeamon/core/electrostatic_potential_orbitals.h
include/FireDeamon/core/irregular_grid_interpolation.h
include/FireDeamon/core/isosurface.h
include/FireDeamon/core/iterate_over_tuple.h
include/FireDeamon/core/orbital_overlap.h
include/FireDeamon/core/parallel_generic.h
include/FireDeamon/core/set_procname.h
include/FireDeamon/core/skin_surface_deamon.h
include/FireDeamon/core/CGAL/ImageIO_impl.h
include/FireDeamon/core/CGAL/Image_3_impl.h
include/FireDeamon/core/halfnum/angular_integral.h
include/FireDeamon/core/halfnum/radial_integral.h
include/FireDeamon/visualize/interface.h
src/core/arbitrary_grid_local_minima.cpp
src/core/constants.cpp
src/core/electron_density.cpp
src/core/electrostatic_potential_charges.cpp
src/core/electrostatic_potential_orbitals.cpp
src/core/irregular_grid_interpolation.cpp
src/core/isosurface.cpp
src/core/orbital_overlap.cpp
src/core/parallel_generic.cpp
src/core/set_procname.cpp
src/core/skin_surface_deamon.cpp
src/core/halfnum/angular_integral.cpp
src/core/halfnum/radial_integral.cpp
src/visualize/interface.cpp