Metadata-Version: 2.1
Name: FireDeamon
Version: 0.1.2
Summary: Misc routines for the ManipulateAggregates package
Home-page: https://github.com/razziel89/libFireDeamon
Author: Torsten Sachse
License: UNKNOWN
Platform: UNKNOWN
Classifier: Development Status :: 4 - Beta
Classifier: Intended Audience :: Developers
Classifier: Intended Audience :: Science/Research
Classifier: License :: OSI Approved :: GNU General Public License v3 or later (GPLv3+)
Classifier: Natural Language :: English
Classifier: Operating System :: POSIX :: Linux
Classifier: Programming Language :: C++
Classifier: Programming Language :: Python :: 3.8
Classifier: Programming Language :: Python :: 3 :: Only
